protaska/__init__.py
protaska/describer.py
protaska/ideate.py
protaska/data/__init__.py
protaska/data/data_utils.py
protaska/data/ingestion.py
protaska/data/loader.py
ProTaska_GPT-0.0.12.dist-info/LICENSE
ProTaska_GPT-0.0.12.dist-info/METADATA
ProTaska_GPT-0.0.12.dist-info/WHEEL
ProTaska_GPT-0.0.12.dist-info/top_level.txt
ProTaska_GPT-0.0.12.dist-info/RECORD
