Metadata-Version: 2.1
Name: ProTaska-GPT
Version: 0.0.12
Summary: Unleash the Potential of Datasets with Intelligent Tasks, Tutorials, and Algorithm Recommendations.
Home-page: https://github.com/AmanPriyanshu/protaska-gpt
Author: Aman Priyanshu, Supriti Vijay
Author-email: amanpriyanshusms2001@gmail.com
Classifier: Development Status :: 3 - Alpha
Classifier: Intended Audience :: Developers
Classifier: License :: OSI Approved :: MIT License
Classifier: Programming Language :: Python :: 3
Classifier: Programming Language :: Python :: 3.7
Classifier: Programming Language :: Python :: 3.8
Classifier: Programming Language :: Python :: 3.9
License-File: LICENSE
Requires-Dist: langchain
Requires-Dist: numpy
Requires-Dist: pandas
Requires-Dist: colorama
Requires-Dist: wikipedia
Requires-Dist: openai
Requires-Dist: datasets
Requires-Dist: tiktoken
